{ "compressionlevel":-1,
 "height":10,
 "infinite":false,
 "layers":[
        {
         "data":[5728, 5729, 5633, 5634, 5635, 0, 0, 0, 0, 0, 7200, 7201, 0, 0, 0, 0, 0, 0, 0, 0,
            5728, 5729, 5658, 5658, 5660, 0, 0, 0, 0, 0, 7250, 7251, 0, 0, 0, 0, 0, 0, 0, 0,
            5728, 5658, 5658, 5658, 5685, 0, 0, 0, 0, 0, 7300, 7301, 0, 0, 0, 0, 0, 0, 0, 0,
            5728, 5658, 5658, 5709, 5710, 0, 0, 0, 0, 0, 7350, 7351, 0, 0, 0, 0, 0, 0, 0, 0,
            5728, 5729, 5658, 5658, 5610, 0, 0, 0, 0, 0, 0, 0, 0, 0, 0, 0, 0, 0, 0, 0,
            5658, 5658, 5658, 5658, 5610, 0, 0, 0, 0, 0, 0, 0, 0, 0, 0, 0, 0, 0, 0, 0,
            5728, 5658, 5658, 5658, 5635, 0, 0, 0, 0, 0, 0, 0, 0, 0, 0, 0, 0, 0, 0, 0,
            5753, 5754, 5658, 5658, 5660, 0, 0, 0, 0, 0, 0, 0, 0, 0, 0, 0, 0, 0, 0, 0,
            5778, 5658, 5658, 5684, 5685, 0, 0, 0, 0, 0, 0, 0, 0, 0, 0, 0, 0, 0, 0, 0,
            5803, 5658, 5708, 5709, 5710, 0, 0, 0, 0, 0, 0, 0, 0, 0, 0, 0, 0, 0, 0, 0],
         "height":10,
         "id":2,
         "name":"Tile Layer 3",
         "opacity":1,
         "type":"tilelayer",
         "visible":true,
         "width":20,
         "x":0,
         "y":0
        }, 
        {
         "data":[6114, 6115, 0, 4979, 4980, 5077, 5079, 338, 339, 340, 339, 340, 339, 340, 341, 5079, 5078, 5079, 5079, 5079,
            6127, 6128, 0, 5004, 5005, 5078, 5079, 380, 381, 382, 381, 382, 381, 382, 383, 5103, 5103, 5079, 5078, 5079,
            6140, 6141, 6196, 5029, 5030, 5079, 5079, 422, 423, 424, 423, 424, 423, 424, 425, 5103, 5103, 5103, 5078, 5079,
            6196, 0, 4979, 4980, 5079, 5079, 5079, 5079, 5079, 5079, 5103, 5103, 5103, 5103, 5103, 5103, 5103, 5103, 5078, 5079,
            0, 0, 5004, 5005, 5079, 5079, 5079, 5079, 5079, 5079, 5079, 5079, 5077, 5103, 5103, 5103, 5103, 5103, 5103, 5079,
            0, 6118, 5029, 5030, 5079, 5079, 5079, 5079, 5079, 5079, 5079, 5079, 5077, 5103, 5103, 5103, 5103, 5103, 5103, 5079,
            6118, 0, 4979, 5078, 5079, 5079, 5079, 5079, 5079, 5079, 5079, 5079, 5077, 5077, 5103, 5103, 5103, 5103, 5103, 5079,
            0, 0, 5004, 4980, 5078, 5078, 5079, 5079, 5079, 5079, 5079, 5103, 5103, 5103, 5103, 5103, 5103, 5103, 5103, 5079,
            0, 0, 5004, 5005, 5078, 5078, 5079, 5079, 5079, 5079, 5079, 5103, 5103, 5103, 5103, 5103, 5103, 5103, 5103, 5079,
            0, 6196, 5029, 5030, 5078, 5078, 5103, 5103, 5103, 5103, 5103, 5103, 5103, 5102, 5103, 5102, 5102, 5102, 5103, 5104],
         "height":10,
         "id":1,
         "name":"Tile Layer 2",
         "opacity":1,
         "type":"tilelayer",
         "visible":true,
         "width":20,
         "x":0,
         "y":0
        }, 
        {
         "data":[0, 0, 0, 0, 9120, 9121, 9122, 0, 7352, 7353, 7200, 7201, 7352, 7353, 0, 9111, 9112, 9113, 12013, 12014,
            0, 0, 0, 0, 9129, 9130, 9131, 0, 7402, 7403, 7250, 7251, 7402, 7403, 0, 9120, 9121, 9122, 12038, 12039,
            0, 0, 0, 11840, 11841, 11842, 0, 11891, 11892, 11893, 7300, 7301, 11891, 11892, 11893, 9129, 9130, 9131, 11997, 11998,
            0, 0, 0, 11865, 11866, 11867, 0, 11916, 11917, 11918, 7350, 7351, 11916, 11917, 11918, 0, 0, 0, 12022, 12023,
            0, 0, 0, 0, 0, 0, 0, 0, 0, 0, 0, 0, 0, 0, 0, 0, 12470, 12471, 12047, 12048,
            0, 0, 0, 0, 0, 0, 0, 0, 0, 0, 0, 0, 0, 0, 0, 0, 0, 0, 12441, 9094,
            0, 0, 0, 0, 9096, 9097, 9098, 0, 12115, 12116, 0, 0, 12443, 12444, 12115, 12116, 0, 0, 9102, 9103,
            0, 0, 0, 0, 9105, 9106, 9107, 0, 0, 0, 0, 0, 12468, 12469, 0, 12441, 12140, 0, 9111, 9112,
            0, 0, 0, 0, 9114, 9115, 9116, 0, 0, 0, 0, 12441, 11941, 11942, 11943, 0, 11838, 11839, 9120, 9121,
            0, 0, 0, 0, 9123, 9124, 9125, 12164, 0, 12470, 12471, 12472, 11966, 11967, 11968, 12441, 11863, 11864, 9129, 9130],
         "height":10,
         "id":3,
         "name":"Tile Layer 1",
         "opacity":1,
         "type":"tilelayer",
         "visible":true,
         "width":20,
         "x":0,
         "y":0
        }],
 "nextlayerid":4,
 "nextobjectid":1,
 "orientation":"orthogonal",
 "renderorder":"right-down",
 "tiledversion":"1.11.2",
 "tileheight":16,
 "tilesets":[
        {
         "columns":42,
         "firstgid":1,
         "image":"assets/tilesets/coban_tileset/Walls.png",
         "imageheight":800,
         "imagewidth":672,
         "margin":0,
         "name":"walls",
         "spacing":0,
         "tilecount":2100,
         "tileheight":16,
         "tilewidth":16
        }, 
        {
         "columns":42,
         "firstgid":2101,
         "image":"assets/tilesets/coban_tileset/Walls.png",
         "imageheight":800,
         "imagewidth":672,
         "margin":0,
         "name":"walls",
         "spacing":0,
         "tilecount":2100,
         "tileheight":16,
         "tilewidth":16
        }, 
        {
         "columns":25,
         "firstgid":4201,
         "image":"assets/tilesets/coban_tileset/Roofs.png",
         "imageheight":400,
         "imagewidth":400,
         "margin":0,
         "name":"roofs",
         "spacing":0,
         "tilecount":625,
         "tileheight":16,
         "tilewidth":16
        }, 
        {
         "columns":25,
         "firstgid":4826,
         "image":"assets/tilesets/coban_tileset/Floors_Tiles.png",
         "imageheight":416,
         "imagewidth":400,
         "margin":0,
         "name":"floor",
         "spacing":0,
         "tilecount":650,
         "tileheight":16,
         "tilewidth":16
        }, 
        {
         "columns":25,
         "firstgid":5476,
         "image":"assets/tilesets/coban_tileset/Water_tiles.png",
         "imageheight":400,
         "imagewidth":400,
         "margin":0,
         "name":"water",
         "spacing":0,
         "tilecount":625,
         "tileheight":16,
         "tilewidth":16
        }, 
        {
         "columns":13,
         "firstgid":6101,
         "image":"assets/tilesets/coban_tileset/Rocks.png",
         "imageheight":304,
         "imagewidth":208,
         "margin":0,
         "name":"rocks",
         "spacing":0,
         "tilecount":247,
         "tileheight":16,
         "tilewidth":16
        }, 
        {
         "columns":50,
         "firstgid":6348,
         "image":"assets/tilesets/coban_tileset/Furniture.png",
         "imageheight":864,
         "imagewidth":800,
         "margin":0,
         "name":"door",
         "spacing":0,
         "tilecount":2700,
         "tileheight":16,
         "tilewidth":16
        }, 
        {
         "columns":9,
         "firstgid":9048,
         "image":"assets/tilesets/coban_tileset/Trees.png",
         "imageheight":160,
         "imagewidth":144,
         "margin":0,
         "name":"trees",
         "spacing":0,
         "tilecount":90,
         "tileheight":16,
         "tilewidth":16
        }, 
        {
         "columns":50,
         "firstgid":9138,
         "image":"assets/tilesets/coban_tileset/Furniture.png",
         "imageheight":864,
         "imagewidth":800,
         "margin":0,
         "name":"door",
         "spacing":0,
         "tilecount":2700,
         "tileheight":16,
         "tilewidth":16
        }, 
        {
         "columns":25,
         "firstgid":11838,
         "image":"assets/tilesets/coban_tileset/Vegetation.png",
         "imageheight":432,
         "imagewidth":400,
         "margin":0,
         "name":"plants",
         "spacing":0,
         "tilecount":675,
         "tileheight":16,
         "tilewidth":16
        }],
 "tilewidth":16,
 "type":"map",
 "version":"1.10",
 "width":20
}